dsci524_group13_quizit/__init__.py
dsci524_group13_quizit/load_questions.py
dsci524_group13_quizit/question_type.py
dsci524_group13_quizit/quizit.py
dsci524_group13_quizit/utils.py
dsci524_group13_quizit-1.1.3.dist-info/LICENSE.md
dsci524_group13_quizit-1.1.3.dist-info/METADATA
dsci524_group13_quizit-1.1.3.dist-info/WHEEL
dsci524_group13_quizit-1.1.3.dist-info/RECORD
