Metadata-Version: 2.3
Name: dsci524_group13_quizit
Version: 1.1.3
Summary: A python package for creating and taking quizzes.
License: GPL-3.0-or-later
Author: Mavis Wong, Shengjia Yu, Sopuruchi Chisom
Requires-Python: >=3.11,<4.0
Classifier: License :: OSI Approved :: GNU General Public License v3 or later (GPLv3+)
Classifier: Programming Language :: Python :: 3
Classifier: Programming Language :: Python :: 3.11
Classifier: Programming Language :: Python :: 3.12
Classifier: Programming Language :: Python :: 3.13
Requires-Dist: pandas (>=2.2.3,<3.0.0)
